django_sqlorm-3.0.0.dist-info/licenses/LICENSE
sqlorm/__init__.py
sqlorm/base.py
sqlorm/cli.py
sqlorm/config.py
sqlorm/exceptions.py
sqlorm/fields.py
sqlorm/app/__init__.py
sqlorm/app/apps.py
sqlorm/app/models.py
django_sqlorm-3.0.0.dist-info/METADATA
django_sqlorm-3.0.0.dist-info/WHEEL
django_sqlorm-3.0.0.dist-info/entry_points.txt
django_sqlorm-3.0.0.dist-info/top_level.txt
django_sqlorm-3.0.0.dist-info/RECORD
