Metadata-Version: 2.4
Name: django-sqlorm
Version: 3.0.0
Summary: Django ORM for standalone Python scripts - Use Django's powerful ORM without a full Django project
Author-email: "S.S.B" <surajsinghbisht054@gmail.com>
License: MIT
Project-URL: Homepage, https://github.com/surajsinghbisht054/sqlorm
Project-URL: Bug Tracker, https://github.com/surajsinghbisht054/sqlorm/issues
Project-URL: Documentation, https://github.com/surajsinghbisht054/sqlorm#readme
Project-URL: Source Code, https://github.com/surajsinghbisht054/sqlorm
Project-URL: Changelog, https://github.com/surajsinghbisht054/sqlorm/blob/main/CHANGELOG.md
Keywords: django,orm,database,sql,sqlite,postgresql,mysql,standalone,script,models,serialization,type-hints
Classifier: Development Status :: 4 - Beta
Classifier: Intended Audience :: Developers
Classifier: License :: OSI Approved :: MIT License
Classifier: Operating System :: OS Independent
Classifier: Programming Language :: Python :: 3
Classifier: Programming Language :: Python :: 3.8
Classifier: Programming Language :: Python :: 3.9
Classifier: Programming Language :: Python :: 3.10
Classifier: Programming Language :: Python :: 3.11
Classifier: Programming Language :: Python :: 3.12
Classifier: Programming Language :: Python :: 3.13
Classifier: Topic :: Database
Classifier: Topic :: Database :: Front-Ends
Classifier: Topic :: Software Development :: Libraries :: Python Modules
Classifier: Framework :: Django
Classifier: Framework :: Django :: 3.2
Classifier: Framework :: Django :: 4.0
Classifier: Framework :: Django :: 4.1
Classifier: Framework :: Django :: 4.2
Classifier: Framework :: Django :: 5.0
Classifier: Typing :: Typed
Requires-Python: >=3.8
License-File: LICENSE
Requires-Dist: Django>=3.2
Provides-Extra: dev
Requires-Dist: pytest>=7.0; extra == "dev"
Requires-Dist: pytest-cov>=4.0; extra == "dev"
Requires-Dist: black>=23.0; extra == "dev"
Requires-Dist: isort>=5.0; extra == "dev"
Requires-Dist: flake8>=6.0; extra == "dev"
Requires-Dist: mypy>=1.0; extra == "dev"
Requires-Dist: django-stubs>=4.0; extra == "dev"
Requires-Dist: pre-commit>=3.0; extra == "dev"
Provides-Extra: postgresql
Requires-Dist: psycopg2-binary>=2.9; extra == "postgresql"
Provides-Extra: mysql
Requires-Dist: mysqlclient>=2.1; extra == "mysql"
Provides-Extra: yaml
Requires-Dist: pyyaml>=6.0; extra == "yaml"
Provides-Extra: all
Requires-Dist: psycopg2-binary>=2.9; extra == "all"
Requires-Dist: mysqlclient>=2.1; extra == "all"
Requires-Dist: pyyaml>=6.0; extra == "all"
Dynamic: license-file
